gsi_installer.py
gsi_protocol_installer-1.2.2.dist-info/METADATA
gsi_protocol_installer-1.2.2.dist-info/WHEEL
gsi_protocol_installer-1.2.2.dist-info/entry_points.txt
gsi_protocol_installer-1.2.2.dist-info/licenses/LICENSE
gsi_protocol_installer-1.2.2.dist-info/RECORD
