Metadata-Version: 2.4
Name: gsi-protocol-installer
Version: 1.2.2
Summary: Installer for GSI-Protocol workflow commands (Claude Code & Codex)
Project-URL: Homepage, https://github.com/CodeMachine0121/GSI-Protocol
Project-URL: Documentation, https://github.com/CodeMachine0121/GSI-Protocol/blob/main/README.md
Project-URL: Repository, https://github.com/CodeMachine0121/GSI-Protocol
Project-URL: Issues, https://github.com/CodeMachine0121/GSI-Protocol/issues
Project-URL: Changelog, https://github.com/CodeMachine0121/GSI-Protocol/blob/main/CODEX_SUPPORT_CHANGELOG.md
Author-email: James Hsueh <asdfg55887@gmail.com>
Maintainer: GSI-Protocol Contributors
License: MIT
License-File: LICENSE
Keywords: ai,bdd,claude,codex,gherkin,gsi-protocol,sdd,spec-driven-development,workflow
Classifier: Development Status :: 4 - Beta
Classifier: Environment :: Console
Classifier: Intended Audience :: Developers
Classifier: License :: OSI Approved :: MIT License
Classifier: Operating System :: OS Independent
Classifier: Programming Language :: Python :: 3
Classifier: Programming Language :: Python :: 3.10
Classifier: Programming Language :: Python :: 3.11
Classifier: Programming Language :: Python :: 3.12
Classifier: Topic :: Software Development :: Code Generators
Classifier: Topic :: Software Development :: Quality Assurance
Classifier: Topic :: Software Development :: Testing
Requires-Python: >=3.10
